pokeapi_sdk/__init__.py
pokeapi_sdk/nature.py
pokeapi_sdk/pokemon.py
pokeapi_sdk/sdk.py
pokeapi_sdk/stat.py
tests/__init__.py
tests/nature_test.py
tests/pokemon_test.py
tests/stat_test.py
pokeapi_sdk_demo-1.0.1.dist-info/LICENSE
pokeapi_sdk_demo-1.0.1.dist-info/METADATA
pokeapi_sdk_demo-1.0.1.dist-info/WHEEL
pokeapi_sdk_demo-1.0.1.dist-info/top_level.txt
pokeapi_sdk_demo-1.0.1.dist-info/RECORD
