Metadata-Version: 2.1
Name: pokeapi-sdk-demo
Version: 1.0.1
Summary: A Python SDK for interacting with PokeAPI
Home-page: https://github.com/bytesguy/pokeapisdkdemo
Author: Adam Hartley
Author-email: git@ahartley.com
Classifier: Development Status :: 3 - Alpha
Classifier: Intended Audience :: Developers
Classifier: License :: OSI Approved :: MIT License
Classifier: Programming Language :: Python :: 3
Classifier: Programming Language :: Python :: 3.7
Classifier: Programming Language :: Python :: 3.8
Classifier: Programming Language :: Python :: 3.9
Classifier: Programming Language :: Python :: 3.10
Classifier: Topic :: Software Development :: Libraries :: Python Modules
License-File: LICENSE
Requires-Dist: requests
